setup.cfg
setup.py
taplytics/__init__.py
taplytics/client.py
taplytics.egg-info/PKG-INFO
taplytics.egg-info/SOURCES.txt
taplytics.egg-info/dependency_links.txt
taplytics.egg-info/requires.txt
taplytics.egg-info/top_level.txt