Metadata-Version: 1.0
Name: taplytics
Version: 0.0.3
Summary: Taplytics Python ALPHA
Home-page: https://github.com/taplytics/taplytics-python/
Author: Taplytics
Author-email: vic@taplytics.com
License: UNKNOWN
Keywords: abtesting,testing,ab,taplytics,optimization,multivariate
Platform: UNKNOWN
